jsongraph/__init__.py
jsongraph/jsongraph.py
jsongraphtree/__init__.py
jsongraphtree/jsongraphtree.py
jsongraphtree-0.2.dist-info/LICENSE
jsongraphtree-0.2.dist-info/METADATA
jsongraphtree-0.2.dist-info/WHEEL
jsongraphtree-0.2.dist-info/entry_points.txt
jsongraphtree-0.2.dist-info/top_level.txt
jsongraphtree-0.2.dist-info/RECORD
