Metadata-Version: 2.1
Name: jsongraphtree
Version: 0.2
Summary: json visualization
Author: sitara
Author-email: 116959197@qq.com
Classifier: Programming Language :: Python :: 3
Classifier: License :: OSI Approved :: MIT License
Classifier: Operating System :: OS Independent
License-File: LICENSE
Requires-Dist: argparse
Requires-Dist: graphviz
